phenodig/.ipynb_checkpoints/__init__-checkpoint.py
phenodig/.ipynb_checkpoints/growthmodels-checkpoint.py
phenodig/.ipynb_checkpoints/logutils-checkpoint.py
phenodig/.ipynb_checkpoints/phenodig-checkpoint.py
phenodig/.ipynb_checkpoints/plotplates-checkpoint.py
phenodig/.ipynb_checkpoints/preproc-checkpoint.py
phenodig/.ipynb_checkpoints/unipruner-checkpoint.py
phenodig/.ipynb_checkpoints/wellfits-checkpoint.py
phenodig/__init__.py
phenodig/assets/.ipynb_checkpoints/PM1-checkpoint.csv
phenodig/assets/.ipynb_checkpoints/PM3B-checkpoint.csv
phenodig/assets/.ipynb_checkpoints/__init__-checkpoint.py
phenodig/assets/PM1.csv
phenodig/assets/PM2A.csv
phenodig/assets/PM3B.csv
phenodig/assets/PM4A.csv
phenodig/assets/__init__.py
phenodig/growthmodels.py
phenodig/logutils.py
phenodig/phenodig.py
phenodig/plotplates.py
phenodig/preproc.py
phenodig/wellfits.py
phenodig-0.3.9.dist-info/LICENSE.txt
phenodig-0.3.9.dist-info/METADATA
phenodig-0.3.9.dist-info/WHEEL
phenodig-0.3.9.dist-info/entry_points.txt
phenodig-0.3.9.dist-info/RECORD
